flask_easy_model/__init__.py
flask_easy_model-0.4.0.dist-info/DESCRIPTION.rst
flask_easy_model-0.4.0.dist-info/METADATA
flask_easy_model-0.4.0.dist-info/RECORD
flask_easy_model-0.4.0.dist-info/WHEEL
flask_easy_model-0.4.0.dist-info/metadata.json
flask_easy_model-0.4.0.dist-info/top_level.txt
