Metadata-Version: 2.0
Name: flask-easy-model
Version: 0.4.0
Summary: A great base model, bringing Django conveniences to Flask
Home-page: https://bitbucket.org/codyc54321/flask_easy_model
Author: Cody Childers
Author-email: cchilder@mail.usf.edu
License: MIT
Platform: UNKNOWN
Classifier: Programming Language :: Python :: 3
